{
  "animaux": [
    { "civil": "Chien",          "undercover": "Loup",           "civilHint": "Animal domestique fidèle à l'homme",               "undercoverHint": "Canidé sauvage vivant en meute" },
    { "civil": "Chat",           "undercover": "Tigre",          "civilHint": "Félin domestique ronronnant sur le canapé",         "undercoverHint": "Grand félin rayé des jungles d'Asie" },
    { "civil": "Éléphant",       "undercover": "Rhinocéros",     "civilHint": "Le plus grand mammifère terrestre avec une trompe", "undercoverHint": "Grand mammifère avec une corne sur le nez" },
    { "civil": "Abeille",        "undercover": "Guêpe",          "civilHint": "Insecte pollinisateur qui fabrique du miel",        "undercoverHint": "Insecte rayé au dard redoutable, sans miel" },
    { "civil": "Requin",         "undercover": "Dauphin",        "civilHint": "Grand prédateur marin aux dents acérées",           "undercoverHint": "Mammifère marin intelligent et joueur" },
    { "civil": "Grenouille",     "undercover": "Crapaud",        "civilHint": "Amphibien lisse qui saute et vit près de l'eau",   "undercoverHint": "Amphibien trapu à la peau verruqueuse" },
    { "civil": "Tortue",         "undercover": "Escargot",       "civilHint": "Reptile lent protégé par une carapace dure",       "undercoverHint": "Petit mollusque lent portant une coquille en spirale" },
    { "civil": "Cerf",           "undercover": "Chevreuil",      "civilHint": "Grand cervidé majestueux avec de grands bois",     "undercoverHint": "Petit cervidé gracieux des forêts européennes" },
    { "civil": "Kangourou",      "undercover": "Wallaby",        "civilHint": "Grand marsupial australien bondissant avec sa poche","undercoverHint": "Petit marsupial australien ressemblant à son grand cousin" },
    { "civil": "Mouton",         "undercover": "Chèvre",         "civilHint": "Animal laineux élevé pour sa toison",              "undercoverHint": "Animal à cornes connu pour son lait et son fromage" },
    { "civil": "Crocodile",      "undercover": "Alligator",      "civilHint": "Grand reptile au museau pointu vivant en eau salée","undercoverHint": "Grand reptile au museau arrondi vivant en eau douce" },
    { "civil": "Perroquet",      "undercover": "Perruche",       "civilHint": "Grand oiseau coloré capable de parler",            "undercoverHint": "Petit oiseau coloré vif et bavard en cage" },
    { "civil": "Aigle",          "undercover": "Faucon",         "civilHint": "Grand rapace majestueux au vol plané impressionnant","undercoverHint": "Rapace rapide spécialisé dans la chasse en piqué" },
    { "civil": "Chameau",        "undercover": "Dromadaire",     "civilHint": "Animal du désert avec deux bosses",                "undercoverHint": "Animal du désert avec une seule bosse" },
    { "civil": "Pingouin",       "undercover": "Manchot",        "civilHint": "Oiseau marin des pôles qui vole",                  "undercoverHint": "Oiseau marin des pôles qui ne vole pas" },
    { "civil": "Panthère",       "undercover": "Léopard",        "civilHint": "Grand félin noir à la robe sombre",                "undercoverHint": "Grand félin tacheté aux rosettes distinctives" },
    { "civil": "Loutre",         "undercover": "Castor",         "civilHint": "Mammifère aquatique joueur au pelage lisse",        "undercoverHint": "Mammifère aquatique constructeur de barrages" },
    { "civil": "Flamant rose",   "undercover": "Héron",          "civilHint": "Grand oiseau rose qui se tient sur une patte",     "undercoverHint": "Grand oiseau gris pêchant dans les marais" },
    { "civil": "Araignée",       "undercover": "Scorpion",       "civilHint": "Arachnide tisseuse de toiles pour capturer ses proies","undercoverHint": "Arachnide à pince et dard venimeux" },
    { "civil": "Baleine",        "undercover": "Cachalot",       "civilHint": "Le plus grand mammifère marin filtrant le krill",  "undercoverHint": "Grand mammifère marin chasseur de calmars géants" },
    { "civil": "Renard",         "undercover": "Blaireau",       "civilHint": "Canidé roux connu pour sa ruse",                   "undercoverHint": "Mustélidé rayé vivant dans des terriers" },
    { "civil": "Poulpe",         "undercover": "Calmar",         "civilHint": "Mollusque marin à huit tentacules",                "undercoverHint": "Mollusque marin à dix tentacules et corps allongé" },
    { "civil": "Hibou",          "undercover": "Chouette",       "civilHint": "Rapace nocturne avec des aigrettes sur la tête",   "undercoverHint": "Rapace nocturne sans aigrettes, plus discret" },
    { "civil": "Saumon",         "undercover": "Truite",         "civilHint": "Poisson migrateur qui remonte les rivières pour pondre","undercoverHint": "Poisson tacheté des rivières froides de montagne" },
    { "civil": "Cobra",          "undercover": "Python",         "civilHint": "Serpent venimeux qui dresse son capuchon",         "undercoverHint": "Grand serpent non venimeux qui étouffe ses proies" },
    { "civil": "Lapin",          "undercover": "Lièvre",         "civilHint": "Petit mammifère domestique aux longues oreilles",  "undercoverHint": "Mammifère sauvage plus grand, coureur très rapide" },
    { "civil": "Gorille",        "undercover": "Chimpanzé",      "civilHint": "Grand singe imposant aux bras puissants",          "undercoverHint": "Grand singe agile au sourire communicatif" },
    { "civil": "Autruche",       "undercover": "Émeu",           "civilHint": "Grand oiseau coureur du désert africain",          "undercoverHint": "Grand oiseau coureur d'Australie" },
    { "civil": "Mouette",        "undercover": "Goéland",        "civilHint": "Petit oiseau de mer blanc aux cris perçants",      "undercoverHint": "Grand oiseau de mer blanc plus imposant" },
    { "civil": "Hyène",          "undercover": "Chacal",         "civilHint": "Carnivore africain au rire caractéristique",       "undercoverHint": "Petit canidé opportuniste des savanes et déserts" },
    { "civil": "Zèbre",          "undercover": "Âne",            "civilHint": "Équidé africain rayé noir et blanc",               "undercoverHint": "Équidé domestique à grandes oreilles" },
    { "civil": "Girafe",         "undercover": "Okapi",          "civilHint": "Animal au très long cou broutant les cimes",       "undercoverHint": "Animal rayé parent de la girafe vivant en forêt" },
    { "civil": "Panda",          "undercover": "Koala",          "civilHint": "Grand ours noir et blanc mangeant du bambou",      "undercoverHint": "Marsupial gris dormant dans les eucalyptus" },
    { "civil": "Méduse",         "undercover": "Anémone de mer", "civilHint": "Invertébré gélatineux flottant dans les courants", "undercoverHint": "Invertébré fixé aux rochers avec de longs tentacules colorés" },
    { "civil": "Pieuvre",        "undercover": "Seiche",         "civilHint": "Céphalopode très intelligent capable de changer de couleur","undercoverHint": "Céphalopode aplati projetant une encre noire" },
    { "civil": "Phoque",         "undercover": "Morse",          "civilHint": "Mammifère marin aux nageoires glissant sur la glace","undercoverHint": "Grand mammifère marin aux longues défenses ivoire" }
  ],

  "nourriture": [
    { "civil": "Café",            "undercover": "Thé",             "civilHint": "Boisson chaude à base de grains torréfiés",           "undercoverHint": "Boisson chaude infusée à partir de feuilles" },
    { "civil": "Pizza",           "undercover": "Tarte flambée",   "civilHint": "Spécialité italienne avec tomate et mozzarella",       "undercoverHint": "Spécialité alsacienne avec crème et lardons" },
    { "civil": "Croissant",       "undercover": "Pain au chocolat","civilHint": "Viennoiserie en forme de lune feuilletée",             "undercoverHint": "Viennoiserie rectangulaire fourrée au cacao" },
    { "civil": "Burger",          "undercover": "Kebab",           "civilHint": "Sandwich américain avec steak haché et pain rond",     "undercoverHint": "Sandwich d'origine turque avec viande grillée en broche" },
    { "civil": "Glace",           "undercover": "Sorbet",          "civilHint": "Dessert glacé crémeux à base de lait",                 "undercoverHint": "Dessert glacé à base de fruits, sans lait" },
    { "civil": "Spaghetti",       "undercover": "Nouilles",        "civilHint": "Pâtes longues et fines d'origine italienne",          "undercoverHint": "Pâtes d'origine asiatique servies en soupe ou sautées" },
    { "civil": "Sushi",           "undercover": "Maki",            "civilHint": "Bouchée de riz vinaigré garnie de poisson cru",        "undercoverHint": "Rouleau de riz et poisson enveloppé dans une algue" },
    { "civil": "Chocolat",        "undercover": "Caramel",         "civilHint": "Douceur brune à base de cacao",                       "undercoverHint": "Confiserie dorée obtenue par cuisson du sucre" },
    { "civil": "Fromage",         "undercover": "Beurre",          "civilHint": "Produit laitier affiné aux mille saveurs",            "undercoverHint": "Matière grasse laitière tartinée sur du pain" },
    { "civil": "Soupe",           "undercover": "Bouillon",        "civilHint": "Plat chaud à base de légumes mixés",                  "undercoverHint": "Liquide chaud obtenu par cuisson de viande ou légumes" },
    { "civil": "Confiture",       "undercover": "Miel",            "civilHint": "Préparation sucrée à base de fruits cuits",           "undercoverHint": "Substance sucrée dorée produite par les abeilles" },
    { "civil": "Pancake",         "undercover": "Crêpe",           "civilHint": "Galette épaisse et moelleuse d'origine américaine",   "undercoverHint": "Galette fine et plate d'origine bretonne" },
    { "civil": "Baguette",        "undercover": "Pain de mie",     "civilHint": "Pain français long et croustillant",                  "undercoverHint": "Pain moelleux en tranches pour les toasts" },
    { "civil": "Bière",           "undercover": "Cidre",           "civilHint": "Boisson alcoolisée fermentée à base d'orge et de houblon","undercoverHint": "Boisson alcoolisée pétillante à base de pommes" },
    { "civil": "Champagne",       "undercover": "Prosecco",        "civilHint": "Vin pétillant français de la région champenoise",     "undercoverHint": "Vin pétillant italien de la région de Vénétie" },
    { "civil": "Muffin",          "undercover": "Cupcake",         "civilHint": "Petit gâteau individuel moelleux sans glaçage",       "undercoverHint": "Petit gâteau individuel surmonté de crème colorée" },
    { "civil": "Fondue",          "undercover": "Raclette",        "civilHint": "Plat alpin où l'on trempe le pain dans le fromage fondu","undercoverHint": "Plat alpin où l'on fait fondre du fromage à la spatule" },
    { "civil": "Framboise",       "undercover": "Groseille",       "civilHint": "Petit fruit rouge en drupe poussant en touffes",      "undercoverHint": "Petit fruit rouge acidulé en grappes" },
    { "civil": "Citron",          "undercover": "Citron vert",     "civilHint": "Agrume jaune au goût acide utilisé en pâtisserie",    "undercoverHint": "Agrume vert au parfum frais, roi des cocktails" },
    { "civil": "Macaron",         "undercover": "Financier",       "civilHint": "Petit gâteau coloré à la ganache entre deux coques",  "undercoverHint": "Petit gâteau rectangulaire moelleux à la poudre d'amandes" },
    { "civil": "Yaourt",          "undercover": "Fromage blanc",   "civilHint": "Lait fermenté en pot individuel",                     "undercoverHint": "Produit laitier frais onctueux plus épais" },
    { "civil": "Pistache",        "undercover": "Noix de cajou",   "civilHint": "Petite noix verte croquante aux teintes violacées",   "undercoverHint": "Noix en forme de haricot originaire du Brésil" },
    { "civil": "Tarte tatin",     "undercover": "Tarte aux pommes","civilHint": "Tarte aux pommes caramélisées servie à l'envers",    "undercoverHint": "Tarte classique aux pommes sur fond de pâte" },
    { "civil": "Brioche",         "undercover": "Kouglof",         "civilHint": "Pain brioché moelleux riche en beurre et oeufs",      "undercoverHint": "Gâteau alsacien en couronne avec raisins secs" },
    { "civil": "Pesto",           "undercover": "Tapenade",        "civilHint": "Sauce vibrante à base de basilic, parmesan et pignons","undercoverHint": "Sauce provençale à base d'olives et câpres" },
    { "civil": "Whisky",          "undercover": "Rhum",            "civilHint": "Alcool de grain vieilli en fût, d'origine écossaise", "undercoverHint": "Alcool de canne à sucre des Caraïbes" },
    { "civil": "Bretzel",         "undercover": "Grissini",        "civilHint": "Pain torsadé salé d'origine allemande",              "undercoverHint": "Fin bâtonnet de pain croustillant d'origine italienne" },
    { "civil": "Pomme",           "undercover": "Poire",           "civilHint": "Fruit rond, rouge ou vert, croquant",                "undercoverHint": "Fruit en forme allongée, juteux et sucré" },
    { "civil": "Croque-monsieur", "undercover": "Club sandwich",   "civilHint": "Sandwich chaud gratiné au fromage d'origine française","undercoverHint": "Triple sandwich froid avec bacon, tomate et mayo" },
    { "civil": "Lasagnes",        "undercover": "Moussaka",        "civilHint": "Plat de pâtes en couches gratiné à la bolognaise",   "undercoverHint": "Gratin grec à l'aubergine et à la viande hachée" },
    { "civil": "Ratatouille",     "undercover": "Bouillabaisse",   "civilHint": "Ragoût provençal de légumes d'été mijotés",          "undercoverHint": "Soupe de poissons marseillaise servie avec du pain" },
    { "civil": "Guacamole",       "undercover": "Tzatziki",        "civilHint": "Sauce mexicaine verte à base d'avocat et citron vert","undercoverHint": "Sauce grecque au yaourt, concombre et ail" },
    { "civil": "Tacos",           "undercover": "Burrito",         "civilHint": "Galette de maïs garnie et pliée ouverte",            "undercoverHint": "Grande galette de blé enroulée autour de la garniture" },
    { "civil": "Dim sum",         "undercover": "Gyoza",           "civilHint": "Bouchées chinoises vapeur dans des paniers en bambou","undercoverHint": "Raviolis japonais poêlés croustillants" },
    { "civil": "Limonade",        "undercover": "Orangina",        "civilHint": "Boisson gazeuse au citron classique",                "undercoverHint": "Boisson gazeuse à l'orange avec pulpe" },
    { "civil": "Magnum",          "undercover": "Esquimau",        "civilHint": "Glace sur bâtonnet enrobée de chocolat épais",       "undercoverHint": "Glace à l'eau ou à la crème sur un petit bâtonnet" },
    { "civil": "Éclair",          "undercover": "Paris-Brest",     "civilHint": "Pâtisserie allongée en pâte à choux avec crème",     "undercoverHint": "Pâtisserie ronde en pâte à choux à la praline" }
  ],

  "sports": [
    { "civil": "Football",        "undercover": "Rugby",           "civilHint": "Sport où l'on frappe un ballon rond avec les pieds","undercoverHint": "Sport où l'on porte un ballon ovale à la main" },
    { "civil": "Skateboard",      "undercover": "Roller",          "civilHint": "Planche à roulettes pour glisser debout",           "undercoverHint": "Chaussures à roulettes pour patiner" },
    { "civil": "Escalade",        "undercover": "Randonnée",       "civilHint": "Sport consistant à grimper des parois rocheuses",   "undercoverHint": "Activité de marche en pleine nature sur des sentiers" },
    { "civil": "Natation",        "undercover": "Plongée",         "civilHint": "Sport aquatique en surface avec des nages codifiées","undercoverHint": "Activité subaquatique avec bouteilles d'air" },
    { "civil": "Tennis",          "undercover": "Badminton",       "civilHint": "Sport de raquette avec une balle sur un court",     "undercoverHint": "Sport de raquette avec un volant léger" },
    { "civil": "Boxe",            "undercover": "Karaté",          "civilHint": "Art martial de coups de poings sur un ring",        "undercoverHint": "Art martial japonais de coups de poings et pieds" },
    { "civil": "Yoga",            "undercover": "Pilates",         "civilHint": "Pratique de poses et de respiration d'origine indienne","undercoverHint": "Méthode de renforcement musculaire profond" },
    { "civil": "Ski",             "undercover": "Snowboard",       "civilHint": "Sport d'hiver sur deux planches parallèles",        "undercoverHint": "Sport d'hiver sur une seule planche large" },
    { "civil": "Surf",            "undercover": "Wakeboard",       "civilHint": "Sport de glisse sur les vagues de l'océan",         "undercoverHint": "Sport de glisse sur l'eau tiré par un bateau" },
    { "civil": "Handball",        "undercover": "Waterpolo",       "civilHint": "Sport collectif où l'on lance un ballon dans un but","undercoverHint": "Sport collectif joué dans l'eau avec un ballon" },
    { "civil": "Judo",            "undercover": "Lutte",           "civilHint": "Art martial japonais basé sur les projections au sol","undercoverHint": "Sport de combat où l'on cherche à terrasser l'adversaire" },
    { "civil": "Tir à l'arc",     "undercover": "Fléchettes",      "civilHint": "Sport de précision avec arc et flèches vers une cible","undercoverHint": "Jeu de précision avec petits projectiles vers une cible ronde" },
    { "civil": "Volleyball",      "undercover": "Beach-volley",    "civilHint": "Sport collectif sur parquet avec filet et six joueurs","undercoverHint": "Sport collectif sur sable avec deux joueurs par équipe" },
    { "civil": "Bowling",         "undercover": "Pétanque",        "civilHint": "Jeu où l'on roule une boule pour renverser des quilles","undercoverHint": "Jeu où l'on lance des boules près d'un cochonnet" },
    { "civil": "Cyclisme",        "undercover": "Triathlon",       "civilHint": "Sport de compétition sur vélo sur route ou piste",  "undercoverHint": "Sport enchaînant natation, vélo et course à pied" },
    { "civil": "Équitation",      "undercover": "Polo",            "civilHint": "Art de monter à cheval avec grâce et technique",    "undercoverHint": "Sport à cheval où l'on frappe une balle avec un maillet" },
    { "civil": "Golf",            "undercover": "Croquet",         "civilHint": "Sport où l'on frappe une balle dans un trou avec un club","undercoverHint": "Jeu où l'on frappe des boules dans des arceaux" },
    { "civil": "Planche à voile", "undercover": "Kitesurf",        "civilHint": "Glisse sur l'eau grâce à une voile fixée à une planche","undercoverHint": "Glisse sur l'eau propulsée par un cerf-volant géant" },
    { "civil": "Billard",         "undercover": "Snooker",         "civilHint": "Jeu de table avec trois boules et une queue en bois","undercoverHint": "Jeu de table britannique avec 22 boules colorées" },
    { "civil": "Parachutisme",    "undercover": "Base jump",       "civilHint": "Saut en chute libre depuis un avion avec un parachute","undercoverHint": "Saut depuis une falaise ou immeuble avec ouverture rapide" },
    { "civil": "Escrime",         "undercover": "Kendo",           "civilHint": "Sport de combat à l'épée d'origine européenne",     "undercoverHint": "Art martial japonais au sabre en bambou" },
    { "civil": "Taekwondo",       "undercover": "Jiu-jitsu",       "civilHint": "Art martial coréen famous pour ses coups de pieds sautés","undercoverHint": "Art martial brésilien de combat au sol" },
    { "civil": "Aviron",          "undercover": "Kayak",           "civilHint": "Sport nautique avec des rames dans un bateau long", "undercoverHint": "Sport nautique avec une pagaie double dans une embarcation fermée" },
    { "civil": "Pentathlon",      "undercover": "Décathlon",       "civilHint": "Compétition olympique combinant cinq disciplines",  "undercoverHint": "Compétition olympique combinant dix disciplines d'athlétisme" },
    { "civil": "Patinage artistique","undercover": "Danse sur glace","civilHint": "Discipline solo ou en couple avec sauts et pirouettes","undercoverHint": "Discipline en couple sur glace inspirée de la danse de salon" },
    { "civil": "Sumo",            "undercover": "Gréco-romaine",   "civilHint": "Lutte japonaise opposant deux lutteurs corpulents", "undercoverHint": "Lutte olympique n'autorisant que les prises au-dessus de la ceinture" },
    { "civil": "Squash",          "undercover": "Racquetball",     "civilHint": "Sport de raquette dans un couloir fermé avec une balle dure","undercoverHint": "Sport de raquette américain dans un couloir fermé avec une balle creuse" }
  ],

  "voyage": [
    { "civil": "Montagne",    "undercover": "Colline",          "civilHint": "Relief très élevé souvent enneigé au sommet",        "undercoverHint": "Petite élévation de terrain arrondie" },
    { "civil": "Océan",       "undercover": "Mer",              "civilHint": "Immense étendue d'eau salée entre les continents",   "undercoverHint": "Étendue d'eau salée plus petite, souvent bordée de terres" },
    { "civil": "Avion",       "undercover": "Hélicoptère",      "civilHint": "Aéronef à ailes fixes pour les longs trajets",      "undercoverHint": "Aéronef à hélices pouvant décoller verticalement" },
    { "civil": "Paris",       "undercover": "Londres",          "civilHint": "Capitale française avec la Tour Eiffel",             "undercoverHint": "Capitale britannique avec Big Ben" },
    { "civil": "Métro",       "undercover": "Tramway",          "civilHint": "Transport en commun souterrain en ville",            "undercoverHint": "Transport en commun sur rails en surface" },
    { "civil": "Sac à dos",   "undercover": "Valise",           "civilHint": "Bagage porté sur les épaules pour les randonnées",   "undercoverHint": "Bagage rigide à roulettes pour les voyages" },
    { "civil": "Tour Eiffel", "undercover": "Statue de la Liberté","civilHint": "Monument en fer de 300 m au cœur de Paris",     "undercoverHint": "Monument offert par la France, dressé à New York" },
    { "civil": "Yacht",       "undercover": "Voilier",          "civilHint": "Bateau de luxe à moteur pour les croisières",       "undercoverHint": "Bateau propulsé par le vent grâce à ses voiles" },
    { "civil": "Gondole",     "undercover": "Canoë",            "civilHint": "Embarcation vénitienne conduite à la rame",          "undercoverHint": "Petite embarcation légère propulsée à la pagaie" },
    { "civil": "Rome",        "undercover": "Naples",           "civilHint": "Capitale italienne avec le Colisée et le Vatican",   "undercoverHint": "Ville du sud de l'Italie berceau de la pizza" },
    { "civil": "Tokyo",       "undercover": "Osaka",            "civilHint": "Capitale japonaise ultramoderne et tentaculaire",    "undercoverHint": "Deuxième ville du Japon, capitale de la gastronomie" },
    { "civil": "Sahara",      "undercover": "Gobi",             "civilHint": "Plus grand désert chaud du monde en Afrique",        "undercoverHint": "Grand désert froid d'Asie centrale" },
    { "civil": "Aéroport",    "undercover": "Gare",             "civilHint": "Infrastructure accueillant les avions et les passagers","undercoverHint": "Infrastructure accueillant les trains et les voyageurs" },
    { "civil": "Marché",      "undercover": "Bazar",            "civilHint": "Lieu de vente en plein air avec étals de produits frais","undercoverHint": "Marché couvert oriental avec boutiques labyrinthiques" },
    { "civil": "Château",     "undercover": "Manoir",           "civilHint": "Grande demeure fortifiée de la noblesse médiévale",  "undercoverHint": "Grande maison de campagne élégante et bourgeoise" },
    { "civil": "Igloo",       "undercover": "Tente",            "civilHint": "Habitation en blocs de glace des Inuits",            "undercoverHint": "Abri portatif en toile pour le camping" },
    { "civil": "New York",    "undercover": "Chicago",          "civilHint": "Mégapole américaine avec Central Park et Times Square","undercoverHint": "Ville américaine des Grands Lacs connue pour son jazz" },
    { "civil": "Barcelone",   "undercover": "Madrid",           "civilHint": "Ville espagnole avec la Sagrada Familia et la Rambla","undercoverHint": "Capitale espagnole avec le Prado et le Retiro" },
    { "civil": "Marrakech",   "undercover": "Essaouira",        "civilHint": "Ville rouge du Maroc avec la Djemaa el-Fna",         "undercoverHint": "Port bleu et blanc du Maroc balayé par le vent" },
    { "civil": "Venise",      "undercover": "Amsterdam",        "civilHint": "Ville italienne sur l'eau parcourue de canaux",      "undercoverHint": "Capitale néerlandaise avec canaux et vélos" },
    { "civil": "Croisière",   "undercover": "Ferry",            "civilHint": "Long voyage en bateau de luxe avec escales",         "undercoverHint": "Traversée courte en bateau pour traverser un bras de mer" },
    { "civil": "Autoroute",   "undercover": "Nationale",        "civilHint": "Voie rapide à péage avec plusieurs files",           "undercoverHint": "Route principale traversant villes et campagnes" },
    { "civil": "Camping-car", "undercover": "Caravane",         "civilHint": "Véhicule autonome avec lieu de vie intégré",         "undercoverHint": "Remorque habitable tractée par une voiture" },
    { "civil": "Phare",       "undercover": "Balise",           "civilHint": "Haute tour lumineuse guidant les navires",           "undercoverHint": "Signal lumineux ou sonore pour orienter la navigation" }
  ],

  "technologie": [
    { "civil": "Télévision",     "undercover": "Radio",             "civilHint": "Appareil diffusant des images et du son",            "undercoverHint": "Appareil diffusant uniquement du son" },
    { "civil": "Robot",          "undercover": "Automate",          "civilHint": "Machine programmable capable de réaliser des tâches","undercoverHint": "Mécanisme imitant les mouvements d'un être vivant" },
    { "civil": "Boussole",       "undercover": "GPS",               "civilHint": "Instrument à aiguille magnétique indiquant le nord","undercoverHint": "Appareil électronique de navigation par satellite" },
    { "civil": "Smartphone",     "undercover": "Tablette",          "civilHint": "Petit écran tactile que l'on glisse dans sa poche", "undercoverHint": "Grand écran tactile à poser pour lire ou dessiner" },
    { "civil": "Casque audio",   "undercover": "Écouteurs",         "civilHint": "Appareil porté sur les deux oreilles pour écouter", "undercoverHint": "Petits embouts qui s'insèrent dans les oreilles" },
    { "civil": "Drone",          "undercover": "Cerf-volant",       "civilHint": "Appareil volant téléguidé avec caméra embarquée",   "undercoverHint": "Engin volant en tissu tiré par un fil dans le vent" },
    { "civil": "Microscope",     "undercover": "Télescope",         "civilHint": "Instrument optique pour observer l'infiniment petit","undercoverHint": "Instrument optique pour observer l'infiniment loin" },
    { "civil": "Clé USB",        "undercover": "Disque dur externe","civilHint": "Petit dispositif de stockage portable à brancher",  "undercoverHint": "Boîtier de stockage portable avec grande capacité" },
    { "civil": "Sonar",          "undercover": "Radar",             "civilHint": "Système de détection sous-marine par ondes sonores","undercoverHint": "Système de détection aérienne par ondes radio" },
    { "civil": "Câble",          "undercover": "Fibre optique",     "civilHint": "Conducteur métallique transmettant l'électricité",  "undercoverHint": "Filament en verre transmettant des données par la lumière" },
    { "civil": "Fax",            "undercover": "Email",             "civilHint": "Transmission de documents par ligne téléphonique",  "undercoverHint": "Transmission de messages et fichiers par internet" },
    { "civil": "Levier",         "undercover": "Poulie",            "civilHint": "Simple machine permettant de soulever avec moins d'effort","undercoverHint": "Mécanisme à roulette changeant la direction d'un effort" },
    { "civil": "Intelligence artificielle","undercover": "Machine learning","civilHint": "Ensemble de systèmes simulant l'intelligence humaine","undercoverHint": "Technique d'apprentissage automatique pour affiner des prédictions" },
    { "civil": "Réalité virtuelle","undercover": "Réalité augmentée","civilHint": "Immersion totale dans un monde numérique via un casque","undercoverHint": "Superposition d'éléments numériques sur le monde réel" },
    { "civil": "Imprimante 3D",  "undercover": "Scanner 3D",        "civilHint": "Machine créant des objets physiques couche par couche","undercoverHint": "Appareil captant la forme d'un objet pour le numériser" },
    { "civil": "Wi-Fi",          "undercover": "Bluetooth",         "civilHint": "Technologie de réseau sans fil sur longue portée",  "undercoverHint": "Technologie de connexion sans fil de courte portée" },
    { "civil": "Serveur",        "undercover": "Cloud",             "civilHint": "Ordinateur stockant et distribuant des données en réseau","undercoverHint": "Infrastructure distante de stockage accessible par internet" },
    { "civil": "Cryptomonnaie",  "undercover": "NFT",               "civilHint": "Monnaie numérique décentralisée sécurisée par cryptographie","undercoverHint": "Certificat numérique unique certifiant la propriété d'un actif" },
    { "civil": "Ordinateur portable","undercover": "PC de bureau",  "civilHint": "Ordinateur compact transportable avec batterie",    "undercoverHint": "Ordinateur fixe puissant avec tour séparée et écran" },
    { "civil": "Console de salon","undercover": "Console portable", "civilHint": "Station de jeu branchée sur la télévision",        "undercoverHint": "Console de jeu glissée dans les poches et jouée partout" },
    { "civil": "Application",    "undercover": "Logiciel",          "civilHint": "Programme léger conçu pour mobile ou navigateur",  "undercoverHint": "Programme complet installé sur un ordinateur" },
    { "civil": "Satellite",      "undercover": "Station spatiale",  "civilHint": "Engin en orbite retransmettant signaux ou images",  "undercoverHint": "Laboratoire habité orbitant autour de la Terre" }
  ],

  "culture": [
    { "civil": "Guitare",         "undercover": "Ukulélé",          "civilHint": "Instrument à cordes très populaire dans le rock",    "undercoverHint": "Petit instrument à cordes d'origine hawaïenne" },
    { "civil": "Cinéma",          "undercover": "Théâtre",          "civilHint": "Art du grand écran avec des films projetés",         "undercoverHint": "Art de la scène avec des acteurs en direct" },
    { "civil": "Violon",          "undercover": "Violoncelle",      "civilHint": "Instrument à cordes frottées tenu sous le menton",   "undercoverHint": "Instrument à cordes frottées tenu entre les jambes" },
    { "civil": "Orchestre",       "undercover": "Fanfare",          "civilHint": "Ensemble de musiciens classiques avec cordes et vents","undercoverHint": "Ensemble de musiciens jouant des cuivres en défilé" },
    { "civil": "Piano",           "undercover": "Orgue",            "civilHint": "Instrument à touches avec marteaux frappant des cordes","undercoverHint": "Instrument à touches produisant du son par des tuyaux" },
    { "civil": "Trompette",       "undercover": "Saxophone",        "civilHint": "Instrument à vent en cuivre avec pistons",          "undercoverHint": "Instrument à vent en cuivre avec anche et clés" },
    { "civil": "Bibliothèque",    "undercover": "Librairie",        "civilHint": "Lieu public où l'on emprunte des livres gratuitement","undercoverHint": "Commerce où l'on achète des livres" },
    { "civil": "Podcast",         "undercover": "Émission de radio","civilHint": "Contenu audio à écouter en différé quand on veut",   "undercoverHint": "Contenu audio diffusé en direct à une heure précise" },
    { "civil": "Jeu vidéo",       "undercover": "Jeu de plateau",   "civilHint": "Divertissement numérique interactif sur écran",      "undercoverHint": "Divertissement physique joué sur un plateau avec des pions" },
    { "civil": "Festival",        "undercover": "Concert",          "civilHint": "Événement musical multi-artistes sur plusieurs jours","undercoverHint": "Spectacle musical d'un seul artiste ou groupe" },
    { "civil": "Symphonie",       "undercover": "Concerto",         "civilHint": "Composition orchestrale classique en plusieurs mouvements","undercoverHint": "Composition mettant en valeur un soliste face à l'orchestre" },
    { "civil": "Conte",           "undercover": "Fable",            "civilHint": "Récit merveilleux avec héros et créatures magiques", "undercoverHint": "Courte histoire allégorique avec des animaux et une morale" },
    { "civil": "Cirque",          "undercover": "Cabaret",          "civilHint": "Spectacle sous chapiteau avec acrobates et clowns",  "undercoverHint": "Spectacle de variétés dans une salle avec dîner" },
    { "civil": "Danse classique", "undercover": "Danse contemporaine","civilHint": "Art chorégraphique sur pointes avec tutu et code strict","undercoverHint": "Art chorégraphique libre pieds nus sur scène" },
    { "civil": "Opéra",           "undercover": "Comédie musicale", "civilHint": "Spectacle lyrique chanté en musique classique",      "undercoverHint": "Spectacle mêlant chant, danse et dialogues modernes" },
    { "civil": "Accordéon",       "undercover": "Harmonica",        "civilHint": "Instrument à soufflet joué avec les deux mains",     "undercoverHint": "Petit instrument à vent tenu et soufflé avec la bouche" },
    { "civil": "Harpe",           "undercover": "Lyre",             "civilHint": "Grand instrument à cordes verticales joué des deux mains","undercoverHint": "Petit instrument à cordes de l'Antiquité grecque" },
    { "civil": "Encyclopédie",    "undercover": "Dictionnaire",     "civilHint": "Ouvrage de référence expliquant les sujets en détail","undercoverHint": "Ouvrage de référence définissant les mots par ordre alphabétique" },
    { "civil": "Cirque",          "undercover": "Clown",            "civilHint": "Spectacle sous chapiteau avec numéros variés",       "undercoverHint": "Artiste comique maquillé avec un nez rouge" },
    { "civil": "Livre",           "undercover": "Magazine",         "civilHint": "Ouvrage relié contenant une histoire ou un savoir",  "undercoverHint": "Publication périodique illustrée sur divers sujets" },
    { "civil": "Street art",      "undercover": "Graffiti",         "civilHint": "Art urbain reconnu incluant toutes les formes picturales","undercoverHint": "Tag ou dessin peint sur murs sans autorisation" },
    { "civil": "Rap",             "undercover": "R&B",              "civilHint": "Genre musical basé sur le flow et les paroles rythmées","undercoverHint": "Genre musical alliant soul, funk et rythme dansant" },
    { "civil": "Jazz",            "undercover": "Blues",            "civilHint": "Genre musical d'improvisation né à La Nouvelle-Orléans","undercoverHint": "Genre musical mélancolique fondateur du jazz" },
    { "civil": "Photographie",    "undercover": "Peinture",         "civilHint": "Art capturant le réel avec lumière et objectif",    "undercoverHint": "Art créant des images avec pigments et pinceau" }
  ],

  "nature": [
    { "civil": "Soleil",     "undercover": "Lune",          "civilHint": "Étoile qui éclaire nos journées",                      "undercoverHint": "Astre qui illumine nos nuits" },
    { "civil": "Pluie",      "undercover": "Neige",         "civilHint": "Précipitation liquide tombant des nuages",             "undercoverHint": "Précipitation solide formant un manteau blanc" },
    { "civil": "Rose",       "undercover": "Tulipe",        "civilHint": "Fleur épineuse symbole de l'amour",                   "undercoverHint": "Fleur en forme de cloche originaire de Hollande" },
    { "civil": "Volcan",     "undercover": "Geyser",        "civilHint": "Montagne crachant de la lave en éruption",            "undercoverHint": "Source jaillissante d'eau chaude sous pression" },
    { "civil": "Galaxie",    "undercover": "Nébuleuse",     "civilHint": "Vaste ensemble d'étoiles comme la Voie lactée",       "undercoverHint": "Nuage de gaz et poussières dans l'espace" },
    { "civil": "Arc-en-ciel","undercover": "Aurore boréale","civilHint": "Phénomène lumineux multicolore après la pluie",       "undercoverHint": "Phénomène lumineux coloré dans le ciel polaire" },
    { "civil": "Forêt",      "undercover": "Jungle",        "civilHint": "Vaste étendue boisée des régions tempérées",          "undercoverHint": "Végétation dense et tropicale peuplée d'animaux exotiques" },
    { "civil": "Île",        "undercover": "Presqu'île",    "civilHint": "Terre entièrement entourée d'eau",                    "undercoverHint": "Terre presque entièrement entourée d'eau" },
    { "civil": "Falaise",    "undercover": "Dune",          "civilHint": "Paroi rocheuse abrupte surplombant la mer",           "undercoverHint": "Colline de sable sculptée par le vent" },
    { "civil": "Plateau",    "undercover": "Plaine",        "civilHint": "Étendue plate en altitude avec des bords abrupts",    "undercoverHint": "Vaste étendue plate à basse altitude" },
    { "civil": "Comète",     "undercover": "Astéroïde",     "civilHint": "Corps céleste avec une longue traîne lumineuse",      "undercoverHint": "Corps rocheux orbitant autour du Soleil sans traîne" },
    { "civil": "Tornade",    "undercover": "Cyclone",       "civilHint": "Tourbillon atmosphérique violent en entonnoir",       "undercoverHint": "Tempête tropicale rotatoire formée sur l'océan" },
    { "civil": "Cactus",     "undercover": "Agave",         "civilHint": "Plante charnue épineuse du désert stockant l'eau",    "undercoverHint": "Plante grasse aux feuilles pointues servant à faire la tequila" },
    { "civil": "Prairie",    "undercover": "Savane",        "civilHint": "Vaste étendue herbeuse des régions tempérées",        "undercoverHint": "Vaste étendue herbeuse tropicale parsemée d'arbres" },
    { "civil": "Glacier",    "undercover": "Iceberg",       "civilHint": "Masse de glace dans les montagnes qui se déplace lentement","undercoverHint": "Bloc de glace flottant dont la majeure partie est sous l'eau" },
    { "civil": "Rosée",      "undercover": "Givre",         "civilHint": "Gouttelettes d'eau déposées sur les feuilles au matin","undercoverHint": "Dépôt de glace blanc formé par le gel sur les surfaces" },
    { "civil": "Brume",      "undercover": "Brouillard",    "civilHint": "Légère condensation réduisant peu la visibilité",     "undercoverHint": "Épaisse condensation réduisant fortement la visibilité" },
    { "civil": "Coquillage", "undercover": "Corail",        "civilHint": "Enveloppe calcaire d'un mollusque ramassée sur la plage","undercoverHint": "Organisme marin calcaire formant des récifs colorés" },
    { "civil": "Tremblement de terre","undercover": "Tsunami","civilHint": "Secousse violente du sol due aux failles tectoniques","undercoverHint": "Vague géante déclenchée par un séisme sous-marin" },
    { "civil": "Chêne",      "undercover": "Hêtre",         "civilHint": "Arbre majestueux aux glands et à l'écorce crevassée", "undercoverHint": "Grand arbre lisse à l'écorce grise et aux faines" },
    { "civil": "Bambou",     "undercover": "Roseau",        "civilHint": "Plante géante à tige creuse poussant très vite",      "undercoverHint": "Plante aquatique à tige creuse servant à faire des flûtes" },
    { "civil": "Stalactite", "undercover": "Stalagmite",    "civilHint": "Formation calcaire pendant du plafond d'une grotte",  "undercoverHint": "Formation calcaire montant du sol d'une grotte" },
    { "civil": "Grotte",     "undercover": "Gouffre",       "civilHint": "Cavité naturelle creusée dans la roche",             "undercoverHint": "Trou vertical très profond s'ouvrant dans le sol" },
    { "civil": "Tourbière",  "undercover": "Marais",        "civilHint": "Zone humide acide où s'accumule la tourbe",           "undercoverHint": "Zone humide peu profonde avec végétation aquatique" }
  ],

  "mode": [
    { "civil": "Chaussure",  "undercover": "Sandale",       "civilHint": "Couvre-pied fermé pour protéger et marcher",          "undercoverHint": "Chaussure ouverte maintenue par des lanières" },
    { "civil": "Lunettes",   "undercover": "Lentilles",     "civilHint": "Accessoire avec monture posé sur le nez pour mieux voir","undercoverHint": "Petits disques transparents posés sur les yeux" },
    { "civil": "Parapluie",  "undercover": "Parasol",       "civilHint": "Accessoire pour se protéger de la pluie",             "undercoverHint": "Accessoire pour se protéger du soleil" },
    { "civil": "Cravate",    "undercover": "Nœud papillon", "civilHint": "Bande de tissu longue nouée autour du cou",           "undercoverHint": "Accessoire en forme d'ailes porté au col de la chemise" },
    { "civil": "Pyjama",     "undercover": "Robe de chambre","civilHint": "Ensemble de vêtements pour dormir",                  "undercoverHint": "Vêtement d'intérieur ample que l'on enfile au réveil" },
    { "civil": "Imperméable","undercover": "Ciré",          "civilHint": "Manteau long imperméable pour la pluie en ville",     "undercoverHint": "Veste imperméable enduite jaune du marin pêcheur" },
    { "civil": "Smoking",    "undercover": "Costume",       "civilHint": "Tenue formelle noire avec nœud papillon pour le soir","undercoverHint": "Tenue formelle en veste et pantalon assortis" },
    { "civil": "Cardigan",   "undercover": "Pull-over",     "civilHint": "Tricot qui s'ouvre sur le devant avec des boutons",   "undercoverHint": "Tricot sans ouverture que l'on enfile par la tête" },
    { "civil": "Bonnet",     "undercover": "Chapeau",       "civilHint": "Couvre-chef souple en laine tricoté contre le froid", "undercoverHint": "Couvre-chef rigide avec bord et visière" },
    { "civil": "Gants",      "undercover": "Mitaines",      "civilHint": "Couvre-mains avec doigts séparés",                   "undercoverHint": "Couvre-mains avec pouce séparé mais autres doigts ensemble" },
    { "civil": "Écharpe",    "undercover": "Foulard",       "civilHint": "Long tissu tricoté chaud enroulé autour du cou",     "undercoverHint": "Carré de tissu léger noué autour du cou ou de la tête" },
    { "civil": "Ceinture",   "undercover": "Bretelles",     "civilHint": "Bande de cuir ou tissu passant dans les passants du pantalon","undercoverHint": "Deux bandes élastiques sur les épaules pour tenir le pantalon" },
    { "civil": "Botte",      "undercover": "Mocassin",      "civilHint": "Chaussure haute montant jusqu'au genou",             "undercoverHint": "Chaussure basse plate sans lacets ni talon" },
    { "civil": "Bague",      "undercover": "Chevalière",    "civilHint": "Anneau porté à un doigt, souvent orné d'une pierre", "undercoverHint": "Anneau large gravé d'un monogramme ou blason" },
    { "civil": "Sac à main", "undercover": "Pochette",      "civilHint": "Accessoire de mode avec poignée pour porter ses affaires","undercoverHint": "Petit sac plat sans poignée tenu à la main" },
    { "civil": "Manteau",    "undercover": "Pardessus",     "civilHint": "Vêtement long et chaud porté par-dessus les habits", "undercoverHint": "Manteau élégant et ajusté porté par les hommes" },
    { "civil": "Jean",       "undercover": "Chino",         "civilHint": "Pantalon en denim bleu indémodable",                 "undercoverHint": "Pantalon en coton léger beige ou kaki" },
    { "civil": "Bikini",     "undercover": "Monokini",      "civilHint": "Maillot de bain deux pièces pour femme",             "undercoverHint": "Maillot de bain une pièce découpé sur les côtés" },
    { "civil": "Casquette",  "undercover": "Béret",         "civilHint": "Couvre-chef avec visière rigide sur le devant",      "undercoverHint": "Couvre-chef souple et rond sans visière, typiquement français" },
    { "civil": "Tuxedo",     "undercover": "Blazer",        "civilHint": "Veste de soirée élégante à revers en soie",         "undercoverHint": "Veste sport chic à boutons dorés portée sans cravate" },
    { "civil": "Robe",       "undercover": "Combinaison",   "civilHint": "Vêtement féminin d'une pièce couvrant le buste et les jambes","undercoverHint": "Vêtement d'une pièce avec une partie pantalon" }
  ],

  "metiers": [
    { "civil": "Dentiste",    "undercover": "Médecin",           "civilHint": "Spécialiste qui soigne les dents",                  "undercoverHint": "Professionnel de santé qui soigne le corps en général" },
    { "civil": "Cuisinier",   "undercover": "Pâtissier",         "civilHint": "Professionnel qui prépare des plats salés en cuisine","undercoverHint": "Professionnel qui crée des gâteaux et desserts" },
    { "civil": "Architecte",  "undercover": "Urbaniste",         "civilHint": "Professionnel qui conçoit des bâtiments",           "undercoverHint": "Professionnel qui planifie l'organisation des villes" },
    { "civil": "Journaliste", "undercover": "Correspondant",     "civilHint": "Professionnel qui rédige et diffuse l'actualité",   "undercoverHint": "Journaliste basé à l'étranger pour couvrir une région" },
    { "civil": "Chirurgien",  "undercover": "Anesthésiste",      "civilHint": "Médecin qui opère les patients en salle d'opération","undercoverHint": "Médecin qui endort les patients avant une opération" },
    { "civil": "Instituteur", "undercover": "Professeur",        "civilHint": "Enseignant à l'école primaire",                    "undercoverHint": "Enseignant au collège, lycée ou université" },
    { "civil": "Pompier",     "undercover": "Sauveteur",         "civilHint": "Professionnel qui éteint les incendies",            "undercoverHint": "Professionnel qui secourt les personnes en danger" },
    { "civil": "Gendarme",    "undercover": "Policier",          "civilHint": "Agent de sécurité militaire des zones rurales",     "undercoverHint": "Agent de sécurité civil des zones urbaines" },
    { "civil": "Facteur",     "undercover": "Livreur",           "civilHint": "Agent distribuant le courrier postal à domicile",   "undercoverHint": "Agent livrant des colis et commandes à domicile" },
    { "civil": "Notaire",     "undercover": "Avocat",            "civilHint": "Officier public rédigeant les actes officiels",     "undercoverHint": "Juriste défendant les intérêts de ses clients" },
    { "civil": "Sommelier",   "undercover": "Barista",           "civilHint": "Spécialiste des vins conseillant au restaurant",    "undercoverHint": "Spécialiste du café préparant des boissons artisanales" },
    { "civil": "Archéologue", "undercover": "Paléontologue",     "civilHint": "Scientifique qui fouille les vestiges des civilisations passées","undercoverHint": "Scientifique qui étudie les fossiles d'animaux préhistoriques" },
    { "civil": "Acteur",      "undercover": "Mannequin",         "civilHint": "Artiste interprétant des rôles sur scène ou à l'écran","undercoverHint": "Artiste présentant des vêtements sur podium ou shooting" },
    { "civil": "Plongeur",    "undercover": "Scaphandrier",      "civilHint": "Sportif explorant les fonds marins avec bouteilles","undercoverHint": "Professionnel travaillant sous l'eau en combinaison lourde" },
    { "civil": "Vétérinaire", "undercover": "Toiletteur",        "civilHint": "Médecin qui soigne les animaux",                   "undercoverHint": "Professionnel qui coiffe et soigne l'apparence des animaux" },
    { "civil": "Banquier",    "undercover": "Comptable",         "civilHint": "Professionnel gérant les finances et crédits d'une banque","undercoverHint": "Professionnel tenant les comptes d'une entreprise" },
    { "civil": "Diplomate",   "undercover": "Espion",            "civilHint": "Représentant officiel d'un pays à l'étranger",     "undercoverHint": "Agent secret collectant des informations pour un gouvernement" },
    { "civil": "Astronome",   "undercover": "Astronaute",        "civilHint": "Scientifique observant les astres depuis la Terre", "undercoverHint": "Professionnel voyageant dans l'espace" },
    { "civil": "Électricien", "undercover": "Plombier",          "civilHint": "Artisan installant et réparant les circuits électriques","undercoverHint": "Artisan installant et réparant les canalisations d'eau" },
    { "civil": "Réalisateur", "undercover": "Scénariste",        "civilHint": "Professionnel dirigeant le tournage d'un film",     "undercoverHint": "Professionnel écrivant l'histoire et les dialogues d'un film" },
    { "civil": "DJ",          "undercover": "Producteur",        "civilHint": "Artiste mixant des musiques en public sur des platines","undercoverHint": "Professionnel créant des musiques en studio" }
  ],

  "histoire": [
    { "civil": "Pyramide",   "undercover": "Obélisque",     "civilHint": "Monument triangulaire construit par les pharaons",     "undercoverHint": "Colonne de pierre pointue dressée vers le ciel" },
    { "civil": "Samourai",   "undercover": "Chevalier",     "civilHint": "Guerrier japonais au katana et à l'armure laquée",     "undercoverHint": "Guerrier médiéval européen en armure avec une épée" },
    { "civil": "Palais",     "undercover": "Abbaye",        "civilHint": "Résidence royale ou princière aux vastes salles",      "undercoverHint": "Ensemble monastique dirigé par un abbé ou une abbesse" },
    { "civil": "Parchemin",  "undercover": "Papyrus",       "civilHint": "Peau animale séchée utilisée comme support d'écriture","undercoverHint": "Roseau séché utilisé comme support d'écriture en Égypte antique" },
    { "civil": "Bouclier",   "undercover": "Armure",        "civilHint": "Protection portable tenue à la main pour parer les coups","undercoverHint": "Protection complète en métal couvrant tout le corps" },
    { "civil": "Catapulte",  "undercover": "Baliste",       "civilHint": "Machine de guerre lançant des blocs de pierre",        "undercoverHint": "Machine de guerre lançant des traits comme une arbalète géante" },
    { "civil": "Moulin à vent","undercover": "Moulin à eau","civilHint": "Bâtiment utilisant le vent pour moudre le grain",      "undercoverHint": "Bâtiment utilisant un cours d'eau pour moudre le grain" },
    { "civil": "Cathédrale", "undercover": "Mosquée",       "civilHint": "Grand édifice religieux chrétien avec vitraux et clocher","undercoverHint": "Lieu de culte musulman avec minaret et coupole" },
    { "civil": "Phénix",     "undercover": "Dragon",        "civilHint": "Oiseau mythique renaissant de ses cendres",            "undercoverHint": "Créature mythique crachant du feu avec des ailes" },
    { "civil": "Licorne",    "undercover": "Pégase",        "civilHint": "Cheval magique avec une corne sur le front",           "undercoverHint": "Cheval mythologique aux ailes blanches qui vole" },
    { "civil": "Sphinx",     "undercover": "Minotaure",     "civilHint": "Créature mi-lion mi-homme posant des énigmes",         "undercoverHint": "Créature mi-homme mi-taureau enfermée dans un labyrinthe" },
    { "civil": "Sirène",     "undercover": "Naïade",        "civilHint": "Être mythologique mi-femme mi-poisson des océans",     "undercoverHint": "Nymphe habitant les rivières et sources dans la mythologie" },
    { "civil": "Troll",      "undercover": "Ogre",          "civilHint": "Créature du folklore scandinave vivant sous les ponts","undercoverHint": "Géant féroce du folklore mangeant les enfants" },
    { "civil": "Elfe",       "undercover": "Lutin",         "civilHint": "Être fantastique élancé aux oreilles pointues",        "undercoverHint": "Petit être espiègle et malicieux des contes" },
    { "civil": "Vampire",    "undercover": "Zombie",        "civilHint": "Créature nocturne se nourrissant de sang humain",      "undercoverHint": "Mort-vivant errant à la recherche de cerveaux" },
    { "civil": "Fantôme",    "undercover": "Spectre",       "civilHint": "Esprit d'un mort sous forme translucide et blanche",  "undercoverHint": "Apparition d'un défunt souvent maléfique et sombre" },
    { "civil": "Gladiateur", "undercover": "Légionnaire",   "civilHint": "Combattant romain s'affrontant dans l'arène pour le peuple","undercoverHint": "Soldat d'élite de l'armée romaine organisée en légions" },
    { "civil": "Viking",     "undercover": "Normand",       "civilHint": "Guerrier scandinave naviguant et pillant les côtes",   "undercoverHint": "Descendant de Vikings installés en Normandie" },
    { "civil": "Révolution", "undercover": "Révolte",       "civilHint": "Renversement complet du pouvoir en place par le peuple","undercoverHint": "Soulèvement populaire localisé et spontané" },
    { "civil": "Momie",      "undercover": "Sarcophage",    "civilHint": "Corps embaumé et bandeletté d'un pharaon",            "undercoverHint": "Coffre funéraire en pierre ou en or contenant une momie" },
    { "civil": "Templier",   "undercover": "Croisé",        "civilHint": "Moine-soldat médiéval gardant les routes de Jérusalem","undercoverHint": "Chevalier chrétien partant en guerre sainte en Orient" }
  ],

  "quotidien": [
    { "civil": "Miroir",        "undercover": "Vitre",          "civilHint": "Surface réfléchissante montrant son propre reflet",   "undercoverHint": "Surface transparente laissant passer la lumière" },
    { "civil": "Canapé",        "undercover": "Fauteuil",        "civilHint": "Siège long pour plusieurs personnes dans le salon",   "undercoverHint": "Siège individuel confortable avec accoudoirs" },
    { "civil": "Bougie",        "undercover": "Lampe",           "civilHint": "Bâton de cire avec mèche produisant une flamme",     "undercoverHint": "Objet électrique produisant de la lumière" },
    { "civil": "Coussin",       "undercover": "Oreiller",        "civilHint": "Accessoire moelleux décoratif pour le canapé",        "undercoverHint": "Accessoire moelleux sur lequel on pose la tête pour dormir" },
    { "civil": "Cheminée",      "undercover": "Poêle à bois",    "civilHint": "Foyer encastré dans le mur pour brûler du bois",     "undercoverHint": "Appareil de chauffage fermé à bois ou granulés" },
    { "civil": "Hamac",         "undercover": "Transat",         "civilHint": "Toile suspendue entre deux arbres pour se balancer",  "undercoverHint": "Chaise longue pliante pour se prélasser au soleil" },
    { "civil": "Pendule",       "undercover": "Sablier",         "civilHint": "Horloge murale avec aiguilles et cadran",             "undercoverHint": "Instrument de mesure du temps avec du sable qui s'écoule" },
    { "civil": "Savon",         "undercover": "Gel douche",      "civilHint": "Pain solide moussant pour se laver",                  "undercoverHint": "Produit liquide moussant pour se laver sous la douche" },
    { "civil": "Stylo",         "undercover": "Crayon",          "civilHint": "Instrument d'écriture à encre",                     "undercoverHint": "Instrument d'écriture en graphite que l'on taille" },
    { "civil": "Réfrigérateur", "undercover": "Congélateur",     "civilHint": "Appareil ménager pour conserver les aliments au frais","undercoverHint": "Appareil ménager pour conserver les aliments gelés" },
    { "civil": "Grille-pain",   "undercover": "Micro-ondes",     "civilHint": "Appareil faisant griller les tranches de pain",       "undercoverHint": "Appareil réchauffant les aliments par ondes électromagnétiques" },
    { "civil": "Serrure",       "undercover": "Cadenas",         "civilHint": "Mécanisme de fermeture fixe encastré dans une porte", "undercoverHint": "Mécanisme de fermeture portable et amovible" },
    { "civil": "Tirelire",      "undercover": "Coffre-fort",     "civilHint": "Récipient fermé pour économiser des pièces de monnaie","undercoverHint": "Armoire blindée à code pour sécuriser des objets de valeur" },
    { "civil": "Puzzle",        "undercover": "Lego",            "civilHint": "Jeu d'assemblage d'une image à partir de pièces découpées","undercoverHint": "Jeu de construction avec des briques à emboîter" },
    { "civil": "Marteau",       "undercover": "Ciseau à bois",   "civilHint": "Outil pour enfoncer des clous avec une tête en métal","undercoverHint": "Outil tranchant en métal utilisé avec un maillet" },
    { "civil": "Réveil",        "undercover": "Minuteur",        "civilHint": "Horloge qui sonne à l'heure programmée le matin",    "undercoverHint": "Dispositif sonnant après un temps défini de quelques minutes" },
    { "civil": "Brosse à dents","undercover": "Fil dentaire",    "civilHint": "Outil avec poils pour nettoyer les dents",           "undercoverHint": "Fil fin pour nettoyer entre les dents" },
    { "civil": "Aspirateur",    "undercover": "Balai",           "civilHint": "Appareil électrique aspirant la poussière du sol",   "undercoverHint": "Outil manuel à poils pour pousser la poussière" },
    { "civil": "Robinet",       "undercover": "Douche",          "civilHint": "Dispositif d'où coule l'eau du lavabo ou de l'évier","undercoverHint": "Dispositif diffusant l'eau en pluie pour se laver debout" },
    { "civil": "Clé",           "undercover": "Badge",           "civilHint": "Outil métallique ouvrant les serrures mécaniques",   "undercoverHint": "Carte ou puce électronique ouvrant les accès numériques" },
    { "civil": "Poubelle",      "undercover": "Bac de compost",  "civilHint": "Conteneur pour les déchets non recyclables",         "undercoverHint": "Conteneur pour les déchets organiques transformés en engrais" },
    { "civil": "Escalier",      "undercover": "Escalator",       "civilHint": "Suite de marches fixes pour changer d'étage",        "undercoverHint": "Escalier mécanique dans les centres commerciaux" }
  ],

  "manga": [
    { "civil": "Naruto",          "undercover": "Boruto",          "civilHint": "Ninja blond rêvant de devenir Hokage, porteur du renard à neuf queues","undercoverHint": "Fils de Naruto au gel dans les cheveux portant un oeil mystérieux" },
    { "civil": "Goku",            "undercover": "Vegeta",          "civilHint": "Saiyan au coeur pur repoussant ses limites par l'amitié","undercoverHint": "Prince des Saiyans orgueilleux devenant allié" },
    { "civil": "Luffy",           "undercover": "Zoro",            "civilHint": "Capitaine pirate au chapeau de paille cherchant le trésor","undercoverHint": "Épéiste du chapeau de paille manieur de trois sabres" },
    { "civil": "Light Yagami",    "undercover": "L",               "civilHint": "Lycéen génie trouvant un cahier tuant quiconque y est écrit","undercoverHint": "Détective excentrique au sucre rival du porteur du Death Note" },
    { "civil": "Eren Yeager",     "undercover": "Levi Ackerman",   "civilHint": "Jeune soldat dont la rage transforme le monde entier","undercoverHint": "Capitaine légendaire le plus puissant de l'humanité" },
    { "civil": "Pikachu",         "undercover": "Raichu",          "civilHint": "Pokémon souris jaune emblème de la franchise",      "undercoverHint": "Évolution de Pikachu, plus grande et plus puissante" },
    { "civil": "Sailor Moon",     "undercover": "Sailor Mars",     "civilHint": "Guerrière de la lune transformée depuis une lycéenne maladroite","undercoverHint": "Guerrière du feu, prêtresse au caractère fort" },
    { "civil": "Saitama",         "undercover": "Genos",           "civilHint": "Héros chauve qui bat tous ses ennemis en un seul coup","undercoverHint": "Cyborg disciple de Saitama cherchant à le surpasser" },
    { "civil": "Tanjiro",         "undercover": "Zenitsu",         "civilHint": "Tueur de démons cherchant à sauver sa soeur transformée","undercoverHint": "Tueur de démons lâche n'étant redoutable qu'endormi" },
    { "civil": "Kakashi",         "undercover": "Itachi",          "civilHint": "Maître ninja masqué lisant des romans à contenu adulte","undercoverHint": "Génie du clan Uchiha portant un lourd sacrifice secret" },
    { "civil": "Edward Elric",    "undercover": "Alphonse Elric",  "civilHint": "Alchimiste avec un bras et une jambe métalliques suite à une transmutation ratée","undercoverHint": "Frère dont l'âme est liée à une armure géante" },
    { "civil": "Conan Edogawa",   "undercover": "Shinichi Kudo",   "civilHint": "Détective miniaturisé résolvant des crimes sous fausse identité","undercoverHint": "Lycéen prodige avant d'être rapetissé par une drogue" },
    { "civil": "Ryuk",            "undercover": "Rem",             "civilHint": "Dieu de la mort ennuyé ayant laissé tomber son cahier sur Terre","undercoverHint": "Dieu de la mort protégeant Misa Amane avec dévotion" },
    { "civil": "Ichigo Kurosaki", "undercover": "Rukia Kuchiki",   "civilHint": "Substitut shinigami aux cheveux orange portant un grand sabre","undercoverHint": "Shinigami noble transmettant ses pouvoirs à un humain" },
    { "civil": "Natsu Dragneel",  "undercover": "Gray Fullbuster", "civilHint": "Tueur de dragons cracheur de feu de la guilde Fairy Tail","undercoverHint": "Mage des glaces se déshabillant inconsciemment dans Fairy Tail" },
    { "civil": "Chihiro",         "undercover": "Nausicaa",        "civilHint": "Fillette cherchant ses parents dans le monde des bains de Miyazaki","undercoverHint": "Princesse guerrière protégeant son monde des spores toxiques" },
    { "civil": "Totoro",          "undercover": "Catbus",          "civilHint": "Grand esprit de la forêt doux et poilu de Miyazaki","undercoverHint": "Chat-bus à douze pattes transportant les passagers dans Ghibli" },
    { "civil": "Yami Yugi",       "undercover": "Seto Kaiba",      "civilHint": "Double âme ancienne habitant le corps d'un adolescent jouant aux cartes","undercoverHint": "PDG milliardaire rival au deck de Dragons Blancs" },
    { "civil": "Gon Freecss",     "undercover": "Killua Zoldyck",  "civilHint": "Jeune garçon naïf partant chercher son père chasseur légendaire","undercoverHint": "Jeune héritier assassin au sang froid devenant meilleur ami de Gon" },
    { "civil": "Meliodas",        "undercover": "Ban",             "civilHint": "Capitaine des Sept Péchés Capitaux au sourire désinvolte","undercoverHint": "Renard de la Convoitise immortel à la longue lance" },
    { "civil": "Izuku Midoriya",  "undercover": "Katsuki Bakugo",  "civilHint": "Héros sans pouvoir devenant le successeur du symbole de la paix","undercoverHint": "Rival explosif aux mains générant des explosions" },
    { "civil": "Ken Kaneki",      "undercover": "Touka Kirishima", "civilHint": "Étudiant transformé en goule après une greffe d'organe","undercoverHint": "Goule serveuse au café qui cache sa double identité" }
  ],

  "film": [
    { "civil": "Avengers",        "undercover": "Justice League",  "civilHint": "Équipe de super-héros Marvel réunie sur grand écran","undercoverHint": "Équipe de super-héros DC réunie sur grand écran" },
    { "civil": "Titanic",         "undercover": "Armageddon",      "civilHint": "Film catastrophe romantique avec un paquebot qui coule","undercoverHint": "Film catastrophe américain avec un astéroïde menaçant la Terre" },
    { "civil": "Le Parrain",      "undercover": "Casino",          "civilHint": "Saga de la mafia sicilienne réalisée par Coppola",  "undercoverHint": "Film de mafia de Scorsese autour d'un casino de Las Vegas" },
    { "civil": "Star Wars",       "undercover": "Star Trek",       "civilHint": "Saga spatiale avec Jedi, Sith et la Force",         "undercoverHint": "Franchise spatiale avec l'Enterprise et la Fédération" },
    { "civil": "Harry Potter",    "undercover": "Les Animaux Fantastiques","civilHint": "Sorcier au zigzag sur le front affrontant Voldemort à Poudlard","undercoverHint": "Magizoologiste collectant des créatures magiques dans les années 1920" },
    { "civil": "Matrix",          "undercover": "Inception",       "civilHint": "Humain découvrant que la réalité est une simulation","undercoverHint": "Voleur pénétrant les rêves pour y implanter une idée" },
    { "civil": "Shrek",           "undercover": "Kung Fu Panda",   "civilHint": "Ogre vert vivant dans un marais sauvant une princesse","undercoverHint": "Panda maladroit devenant maître kung-fu" },
    { "civil": "Joker",           "undercover": "Batman",          "civilHint": "Clown criminel emblématique né de la souffrance de Gotham","undercoverHint": "Chevalier noir milliardaire protégeant Gotham City" },
    { "civil": "Forrest Gump",    "undercover": "Rain Man",        "civilHint": "Homme simple au coeur immense traversant l'histoire américaine","undercoverHint": "Savant autiste aux capacités de calcul extraordinaires" },
    { "civil": "Interstellar",    "undercover": "Gravity",         "civilHint": "Voyage spatial à travers un trou de ver pour sauver l'humanité","undercoverHint": "Astronaute seule dérivant dans le vide spatial" },
    { "civil": "Pulp Fiction",    "undercover": "Reservoir Dogs",  "civilHint": "Film de Tarantino en chapitres croisés avec des gangsters","undercoverHint": "Premier film de Tarantino avec un hold-up et des couleurs" },
    { "civil": "Le Seigneur des Anneaux","undercover": "Le Hobbit","civilHint": "Trilogie épique de Jackson avec la Communauté détruisant l'Anneau","undercoverHint": "Préquelle de Jackson suivant Bilbo vers la Montagne Solitaire" },
    { "civil": "Jurassic Park",   "undercover": "King Kong",       "civilHint": "Parc thématique de dinosaures recréés par ADN",     "undercoverHint": "Gigantesque primate capturé et amené à New York" },
    { "civil": "Alien",           "undercover": "Predator",        "civilHint": "Extraterrestre parasite à mâchoires intérieures chassant dans l'espace","undercoverHint": "Extraterrestre chasseur traquant des proies pour le sport" },
    { "civil": "Parasite",        "undercover": "Burning",         "civilHint": "Famille pauvre infiltrant une famille riche, Palme d'Or 2019","undercoverHint": "Thriller coréen lent et mystérieux d'un auteur brûlant des serres" },
    { "civil": "Frozen",          "undercover": "Vaiana",          "civilHint": "Reine des neiges aux pouvoirs de glace sauvant sa soeur","undercoverHint": "Jeune polynésienne choisie par l'océan pour une mission" },
    { "civil": "Intouchables",    "undercover": "Patients",        "civilHint": "Film français sur l'amitié entre un riche tétraplégique et son aide","undercoverHint": "Film français sur la rééducation d'un jeune tétraplégique" },
    { "civil": "Amélie Poulain",  "undercover": "Delicatessen",    "civilHint": "Serveuse malicieuse changeant la vie des autres à Montmartre","undercoverHint": "Film de Jeunet dans un immeuble post-apocalyptique où les locataires sont mangés" },
    { "civil": "Mission Impossible","undercover": "James Bond",    "civilHint": "Agent Ethan Hunt réalisant des missions ultra-risquées","undercoverHint": "Agent secret 007 au service de sa Majesté britannique" },
    { "civil": "Gladiator",       "undercover": "Braveheart",      "civilHint": "Général romain devenant gladiateur pour venger sa famille","undercoverHint": "Guerrier écossais menant la révolte contre l'Angleterre" },
    { "civil": "La La Land",      "undercover": "Whiplash",        "civilHint": "Comédie musicale romantique à Los Angeles du réalisateur Chazelle","undercoverHint": "Drame musical sur un batteur de jazz poussé à l'extrême" },
    { "civil": "Toy Story",       "undercover": "Monstres et Cie", "civilHint": "Jouets prenant vie quand leur propriétaire a le dos tourné","undercoverHint": "Monstres chargés d'effrayer des enfants pour récolter leur énergie" },
    { "civil": "L'Exorciste",     "undercover": "Shining",         "civilHint": "Film d'horreur avec une fillette possédée par un démon","undercoverHint": "Film de Kubrick avec un écrivain devenant fou dans un hôtel isolé" },
    { "civil": "Dunkerque",       "undercover": "Il faut sauver le soldat Ryan","civilHint": "Film de Nolan sur l'évacuation des soldats alliés en 1940","undercoverHint": "Film de Spielberg sur le débarquement de Normandie en 1944" }
  ],

  "serie": [
    { "civil": "Game of Thrones", "undercover": "The Last Kingdom","civilHint": "Série médiévale épique avec dragons, trahisons et un Trône de Fer","undercoverHint": "Série médiévale britannique sur les invasions vikings en Angleterre" },
    { "civil": "Breaking Bad",    "undercover": "Ozark",           "civilHint": "Professeur de chimie fabriquant de la drogue et devenant criminel","undercoverHint": "Planificateur financier blanchissant l'argent du cartel au Missouri" },
    { "civil": "Friends",         "undercover": "How I Met Your Mother","civilHint": "Six amis vivant à New York dans des appartements adjacents","undercoverHint": "Père racontant à ses enfants l'histoire de sa rencontre amoureuse" },
    { "civil": "Stranger Things", "undercover": "Dark",            "civilHint": "Enfants affrontant des monstres d'une dimension parallèle dans les 80s","undercoverHint": "Série allemande de voyages temporels sur quatre générations" },
    { "civil": "La Casa de Papel","undercover": "Lupin",           "civilHint": "Braqueurs masqués de Dali prenant la Banque d'Espagne en otage","undercoverHint": "Gentleman cambrioleur français inspiré d'Arsène Lupin" },
    { "civil": "The Office",      "undercover": "Parks and Recreation","civilHint": "Mockumentaire dans une entreprise de papeterie en Pennsylvanie","undercoverHint": "Mockumentaire dans un département des parcs d'une ville de l'Indiana" },
    { "civil": "Peaky Blinders",  "undercover": "Boardwalk Empire","civilHint": "Famille criminelle de Birmingham dans l'Angleterre des années 20","undercoverHint": "Mafieux de Atlantic City pendant la Prohibition américaine" },
    { "civil": "The Witcher",     "undercover": "Shadow and Bone", "civilHint": "Sorceleur errant chassant des monstres dans un monde médiéval-fantastique","undercoverHint": "Jeune fille aux pouvoirs de lumière dans un empire inspiré de la Russie" },
    { "civil": "Squid Game",      "undercover": "Alice in Borderland","civilHint": "Candidats endettés jouant des jeux d'enfants mortels en Corée","undercoverHint": "Joueurs piégés dans Tokyo parallèle jouant des jeux mortels" },
    { "civil": "Black Mirror",    "undercover": "Years and Years",  "civilHint": "Anthologie futuriste sur les dérives de la technologie","undercoverHint": "Série britannique sur une famille face aux crises du futur proche" },
    { "civil": "Chernobyl",       "undercover": "The Loudest Voice","civilHint": "Mini-série sur la catastrophe nucléaire soviétique de 1986","undercoverHint": "Mini-série sur le fondateur de Fox News Roger Ailes" },
    { "civil": "Sherlock",        "undercover": "Elementary",      "civilHint": "Détective britannique modernisé avec Cumberbatch à Londres","undercoverHint": "Détective britannique modernisé à New York avec une femme Watson" },
    { "civil": "Vikings",         "undercover": "Barbares",        "civilHint": "Série épique sur Ragnar Lothbrok et les invasions nordiques","undercoverHint": "Série allemande sur la bataille d'Arminius contre les légions romaines" },
    { "civil": "Westworld",       "undercover": "Humans",          "civilHint": "Parc d'attractions peuplé de robots androïdes prenant conscience","undercoverHint": "Série britannique où des androïdes domestiques développent une conscience" },
    { "civil": "The Crown",       "undercover": "The Queen's Gambit","civilHint": "Drama suivant le règne de la reine Elizabeth II sur plusieurs décennies","undercoverHint": "Mini-série sur une prodige des échecs aux prises avec l'addiction" },
    { "civil": "Narcos",          "undercover": "El Chapo",        "civilHint": "Série sur l'essor et la chute de Pablo Escobar en Colombie","undercoverHint": "Série sur le chef du cartel de Sinaloa mexicain" },
    { "civil": "The Mandalorian", "undercover": "Andor",           "civilHint": "Chasseur de primes en armure protégeant le petit Grogu","undercoverHint": "Espion rebelle dont la série est la plus sombre de Star Wars" },
    { "civil": "Succession",      "undercover": "Billions",        "civilHint": "Guerre de succession dans une famille de magnats de la télévision","undercoverHint": "Duel entre un hedge fund milliardaire et un procureur ambitieux" },
    { "civil": "Euphoria",        "undercover": "Skins",           "civilHint": "Série HBO sur des lycéens américains face à la drogue et l'identité","undercoverHint": "Série britannique culte sur des lycéens au bord du chaos" },
    { "civil": "The Boys",        "undercover": "Invincible",      "civilHint": "Série sur des super-héros corrompus surveillés par une équipe de civils","undercoverHint": "Série animée sur un fils de super-héros découvrant ses pouvoirs" },
    { "civil": "Downton Abbey",   "undercover": "Bridgerton",      "civilHint": "Drama aristocratique anglais autour d'une grande maison du début du XXe siècle","undercoverHint": "Romance de la Régence anglaise avec une famille noble en saison mondaine" },
    { "civil": "Better Call Saul","undercover": "Breaking Bad",    "civilHint": "Préquelle suivant l'avocat raté Jimmy McGill devenant Saul Goodman","undercoverHint": "Professeur de chimie fabriquant de la drogue et devenant criminel" }
  ],

  "cultureg": [
    { "civil": "Atome",           "undercover": "Molécule",        "civilHint": "Plus petite particule d'un élément chimique",       "undercoverHint": "Ensemble d'atomes liés chimiquement formant un corps" },
    { "civil": "Photosynthèse",   "undercover": "Respiration cellulaire","civilHint": "Processus par lequel les plantes fabriquent leur nourriture avec la lumière","undercoverHint": "Processus par lequel les cellules transforment l'oxygène en énergie" },
    { "civil": "Pluton",          "undercover": "Mars",            "civilHint": "Planète naine aux confins du système solaire",       "undercoverHint": "Planète rouge voisine de la Terre objet de missions spatiales" },
    { "civil": "Impressionnisme", "undercover": "Cubisme",         "civilHint": "Mouvement pictural de Monet capturant la lumière changeante","undercoverHint": "Mouvement pictural de Picasso décomposant les formes en géométrie" },
    { "civil": "Démocratie",      "undercover": "République",      "civilHint": "Système où le peuple gouverne directement ou par représentants","undercoverHint": "Système politique sans monarque dirigé par des élus" },
    { "civil": "PIB",             "undercover": "IDH",             "civilHint": "Indicateur mesurant la production économique d'un pays","undercoverHint": "Indicateur mesurant le bien-être humain au-delà de la richesse" },
    { "civil": "Pythagore",       "undercover": "Euclide",         "civilHint": "Mathématicien grec auteur du célèbre théorème sur les triangles rectangles","undercoverHint": "Mathématicien grec fondateur de la géométrie dans les Éléments" },
    { "civil": "ADN",             "undercover": "ARN",             "civilHint": "Molécule portant le code génétique de tous les êtres vivants","undercoverHint": "Molécule transmettant les instructions de l'ADN aux ribosomes" },
    { "civil": "Gravitation",     "undercover": "Électromagnétisme","civilHint": "Force naturelle d'attraction entre les masses",     "undercoverHint": "Force naturelle régissant les charges électriques et les aimants" },
    { "civil": "Trou noir",       "undercover": "Étoile à neutrons","civilHint": "Région de l'espace d'où rien, même la lumière, ne peut s'échapper","undercoverHint": "Astre ultra-dense né de l'explosion d'une étoile massive" },
    { "civil": "Haiku",           "undercover": "Sonnet",          "civilHint": "Poème japonais de 17 syllabes en trois vers",       "undercoverHint": "Poème de 14 vers en deux quatrains et deux tercets" },
    { "civil": "Renaissance",     "undercover": "Baroque",         "civilHint": "Mouvement artistique et intellectuel du XVe-XVIe siècle","undercoverHint": "Style artistique flamboyant et dramatique du XVIIe siècle" },
    { "civil": "Mythologie grecque","undercover": "Mythologie nordique","civilHint": "Panthéon avec Zeus, Athéna et l'Olympe",       "undercoverHint": "Panthéon avec Odin, Thor et Asgard" },
    { "civil": "Laïcité",         "undercover": "Sécularisation",  "civilHint": "Principe de séparation de l'État et de la religion","undercoverHint": "Processus historique de recul du religieux dans la société" },
    { "civil": "Philosophie",     "undercover": "Sociologie",      "civilHint": "Discipline questionnant l'existence, la connaissance et les valeurs","undercoverHint": "Science étudiant les structures et comportements des sociétés humaines" },
    { "civil": "Oxygène",         "undercover": "Azote",           "civilHint": "Gaz essentiel à la respiration et la combustion",   "undercoverHint": "Gaz le plus abondant dans l'atmosphère terrestre (78%)" },
    { "civil": "Logique",         "undercover": "Rhétorique",      "civilHint": "Art du raisonnement correct fondé sur des règles formelles","undercoverHint": "Art de convaincre par le discours et les figures de style" },
    { "civil": "Photon",          "undercover": "Électron",        "civilHint": "Particule élémentaire sans masse transportant la lumière","undercoverHint": "Particule chargée négativement orbitant autour du noyau" },
    { "civil": "Tectonique des plaques","undercover": "Dérive des continents","civilHint": "Théorie expliquant les séismes, volcans et chaînes de montagnes","undercoverHint": "Théorie historique de Wegener sur le mouvement des continents" },
    { "civil": "Thermodynamique", "undercover": "Mécanique des fluides","civilHint": "Science étudiant les échanges de chaleur et d'énergie","undercoverHint": "Science étudiant le comportement des liquides et des gaz en mouvement" },
    { "civil": "Inflation",       "undercover": "Récession",       "civilHint": "Augmentation générale et durable du niveau des prix","undercoverHint": "Baisse de l'activité économique sur au moins deux trimestres" },
    { "civil": "Cerveau",         "undercover": "Système nerveux",  "civilHint": "Organe central de traitement de l'information dans le crâne","undercoverHint": "Réseau de nerfs reliant le cerveau à l'ensemble du corps" }
  ]
}
